tests/vcs_examples/block_level_tests/generic/flop_empty/top_flop.sv
module flop #(parameter WIDTH = 8) (
  input  logic             clk,
  input  logic [WIDTH-1:0] d,
  output logic [WIDTH-1:0] q);

endmodule

module flopenl #(parameter WIDTH = 8, parameter type TYPE=logic [WIDTH-1:0]) (
  input  logic clk, load, en,
  input  TYPE d,
  input  TYPE val,
  output TYPE q);

endmodule

module flopenrc #(parameter WIDTH = 8) (
  input  logic             clk, reset, clear, en,
  input  logic [WIDTH-1:0] d,
  output logic [WIDTH-1:0] q);

endmodule

module flopenr #(parameter WIDTH = 8) (
  input  logic             clk, reset, en,
  input  logic [WIDTH-1:0] d,
  output logic [WIDTH-1:0] q);

endmodule

module flopens #(parameter WIDTH = 8) (
  input  logic             clk, set, en,
  input  logic [WIDTH-1:0] d,
  output logic [WIDTH-1:0] q);

endmodule

module flopen #(parameter WIDTH = 8) (
  input  logic             clk, en,
  input  logic [WIDTH-1:0] d,
  output logic [WIDTH-1:0] q);

endmodule

module flopr #(parameter WIDTH = 8) (
  input  logic             clk, reset,
  input  logic [WIDTH-1:0] d,
  output logic [WIDTH-1:0] q);

endmodule

module synchronizer (
  input  logic clk,
  input  logic d,
  output logic q);

  logic mid;

endmodule

// Top module for testing - doesn't drive or check signals itself, meant for use with external testbench

module top_flop(
  input  logic clk, reset, clear, en, load, set,
  input  logic [7:0] d, val, // Assuming WIDTH=8 for all submodules
  output logic [7:0] q_flop, q_flopenl, q_flopenrc, q_flopenr, q_flopens, q_flopen, q_flopr,
  input  logic d_sync, // Separate input for synchronizer
  output logic q_sync
);

  flop    #(.WIDTH(8)) flop_inst (.clk(clk), .d(d), .q(q_flop));
  flopenl #(.WIDTH(8)) flopenl_inst (.clk(clk), .load(load), .en(en), .d(d), .val(val), .q(q_flopenl));
  flopenrc#(.WIDTH(8)) flopenrc_inst(.clk(clk), .reset(reset), .clear(clear), .en(en), .d(d), .q(q_flopenrc));
  flopenr #(.WIDTH(8)) flopenr_inst(.clk(clk), .reset(reset), .en(en), .d(d), .q(q_flopenr));
  flopens #(.WIDTH(8)) flopens_inst(.clk(clk), .set(set), .en(en), .d(d), .q(q_flopens));
  flopen  #(.WIDTH(8)) flopen_inst (.clk(clk), .en(en), .d(d), .q(q_flopen));
  flopr   #(.WIDTH(8)) flopr_inst  (.clk(clk), .reset(reset), .d(d), .q(q_flopr));
  synchronizer synchronizer_inst (.clk(clk), .d(d_sync), .q(q_sync));
endmodule

tests/vcs_examples/block_level_tests/generic/flop/tb_flop.sv
module tb_flop;

  logic clk, reset, clear, en, load, set;
  logic [7:0] d, val;
  logic d_sync;
  logic [7:0] q_flop, q_flopenl, q_flopenrc, q_flopenr, q_flopens, q_flopen, q_flopr;
  logic q_sync;

  // Instantiate the top module
  top_flop dut(
    .clk(clk), .reset(reset), .clear(clear), .en(en), .load(load), .set(set),
    .d(d), .val(val),
    .q_flop(q_flop), .q_flopenl(q_flopenl), .q_flopenrc(q_flopenrc), .q_flopenr(q_flopenr), .q_flopens(q_flopens), .q_flopen(q_flopen), .q_flopr(q_flopr),
    .d_sync(d_sync), .q_sync(q_sync)
  );

  // Clock generation
  initial begin
    clk = 0;
    forever #5 clk = ~clk; // Generate a clock with 100MHz frequency
  end

  // Apply random inputs and dump VCD
  initial begin
    $dumpfile("tb_flop.vcd");
    $dumpvars(0, tb_flop);

    reset = 1; clear = 0; en = 0; load = 0; set = 0; d = 0; val = 0; d_sync = 0;
    #10 reset = 0; // Release reset after 10ns

    repeat (100) begin
      #10; // Every 10ns, apply new random inputs
      reset = $random; clear = $random; en = $random; load = $random; set = $random;
      d = $urandom%256; val = $urandom%256; d_sync = $urandom%2;
    end

    $finish;
  end
endmodule

tests/vcs_examples/block_level_tests/generic/flop_empty/tb_flop.vcd
$date
	Sat Mar 16 09:50:01 2024
$end

$version
	Synopsys VCS version U-2023.03-SP2-4_Full64
$end

$timescale
	1s
$end

$comment Csum: 1 b8c1dc1d2724083a $end


$scope module tb_flop $end
$var reg 1 ! clk $end
$var reg 1 " reset $end
$var reg 1 # clear $end
$var reg 1 $ en $end
$var reg 1 % load $end
$var reg 1 & set $end
$var reg 8 ' d [7:0] $end
$var reg 8 ( val [7:0] $end
$var reg 1 ) d_sync $end
$var reg 8 * q_flop [7:0] $end
$var reg 8 + q_flopenl [7:0] $end
$var reg 8 , q_flopenrc [7:0] $end
$var reg 8 - q_flopenr [7:0] $end
$var reg 8 . q_flopens [7:0] $end
$var reg 8 / q_flopen [7:0] $end
$var reg 8 0 q_flopr [7:0] $end
$var reg 1 1 q_sync $end

$scope begin unnamed$$_vcs_0 $end
$upscope $end


$scope module dut $end
$var reg 1 2 clk $end
$var reg 1 3 reset $end
$var reg 1 4 clear $end
$var reg 1 5 en $end
$var reg 1 6 load $end
$var reg 1 7 set $end
$var reg 8 8 d [7:0] $end
$var reg 8 9 val [7:0] $end
$var reg 8 : q_flop [7:0] $end
$var reg 8 ; q_flopenl [7:0] $end
$var reg 8 < q_flopenrc [7:0] $end
$var reg 8 = q_flopenr [7:0] $end
$var reg 8 > q_flopens [7:0] $end
$var reg 8 ? q_flopen [7:0] $end
$var reg 8 @ q_flopr [7:0] $end
$var reg 1 A d_sync $end
$var reg 1 B q_sync $end

$scope module flop_inst $end
$var reg 1 C clk $end
$var reg 8 D d [7:0] $end
$var reg 8 E q [7:0] $end
$upscope $end


$scope module flopenl_inst $end
$var reg 1 F clk $end
$var reg 1 G load $end
$var reg 1 H en $end
$var reg 8 I d [7:0] $end
$var reg 8 J val [7:0] $end
$var reg 8 K q [7:0] $end
$upscope $end


$scope module flopenrc_inst $end
$var reg 1 L clk $end
$var reg 1 M reset $end
$var reg 1 N clear $end
$var reg 1 O en $end
$var reg 8 P d [7:0] $end
$var reg 8 Q q [7:0] $end
$upscope $end


$scope module flopenr_inst $end
$var reg 1 R clk $end
$var reg 1 S reset $end
$var reg 1 T en $end
$var reg 8 U d [7:0] $end
$var reg 8 V q [7:0] $end
$upscope $end


$scope module flopens_inst $end
$var reg 1 W clk $end
$var reg 1 X set $end
$var reg 1 Y en $end
$var reg 8 Z d [7:0] $end
$var reg 8 [ q [7:0] $end
$upscope $end


$scope module flopen_inst $end
$var reg 1 \ clk $end
$var reg 1 ] en $end
$var reg 8 ^ d [7:0] $end
$var reg 8 _ q [7:0] $end
$upscope $end


$scope module flopr_inst $end
$var reg 1 ` clk $end
$var reg 1 a reset $end
$var reg 8 b d [7:0] $end
$var reg 8 c q [7:0] $end
$upscope $end


$scope module synchronizer_inst $end
$var reg 1 d clk $end
$var reg 1 e d $end
$var reg 1 f q $end
$var reg 1 g mid $end
$upscope $end

$upscope $end

$upscope $end

$enddefinitions $end

#0
$dumpvars
0#
0!
0)
04
0A
05
06
xB
13
07
0$
0]
0H
0G
0T
1S
0N
0O
1M
0Y
0X
1a
0%
xg
x1
1"
0&
0e
xf
b00000000 I
bxxxxxxxx K
b00000000 J
b00000000 '
b00000000 8
bxxxxxxxx :
bxxxxxxxx ?
bxxxxxxxx ;
bxxxxxxxx =
bxxxxxxxx <
bxxxxxxxx >
bxxxxxxxx @
b00000000 9
b00000000 D
b00000000 ^
bxxxxxxxx _
b00000000 U
bxxxxxxxx V
b00000000 P
bxxxxxxxx Q
b00000000 Z
bxxxxxxxx [
b00000000 b
bxxxxxxxx c
bxxxxxxxx E
bxxxxxxxx *
bxxxxxxxx /
bxxxxxxxx +
bxxxxxxxx -
bxxxxxxxx ,
bxxxxxxxx .
bxxxxxxxx 0
b00000000 (
02
0C
0F
0L
0R
0W
0\
0`
0d
$end
#5
1!
12
1C
1F
1L
1R
1W
1\
1`
1d
#10
0"
03
0a
0S
0M
0!
02
0C
0F
0L
0R
0W
0\
0`
0d
#15
1!
12
1C
1F
1L
1R
1W
1\
1`
1d
#20
1#
14
1N
1$
15
1]
1Y
1T
1O
1H
1%
16
1G
1&
17
1X
b00010011 '
b00010011 8
b00010011 b
b00010011 ^
b00010011 Z
b00010011 U
b00010011 P
b00010011 I
b00010011 D
b01110000 (
b01110000 9
b01110000 J
1)
1A
1e
0!
02
0C
0F
0L
0R
0W
0\
0`
0d
#25
1!
12
1C
1F
1L
1R
1W
1\
1`
1d
#30
1"
13
1a
1S
1M
0$
05
0]
0Y
0T
0O
0H
b11100010 '
b11100010 8
b11100010 b
b11100010 ^
b11100010 Z
b11100010 U
b11100010 P
b11100010 I
b11100010 D
b10010111 (
b10010111 9
b10010111 J
0!
02
0C
0F
0L
0R
0W
0\
0`
0d
#35
1!
12
1C
1F
1L
1R
1W
1\
1`
1d
#40
0"
03
0a
0S
0M
1$
15
1]
1Y
1T
1O
1H
0%
06
0G
b11000101 '
b11000101 8
b11000101 b
b11000101 ^
b11000101 Z
b11000101 U
b11000101 P
b11000101 I
b11000101 D
b11101100 (
b11101100 9
b11101100 J
0)
0A
0e
0!
02
0C
0F
0L
0R
0W
0\
0`
0d
#45
1!
12
1C
1F
1L
1R
1W
1\
1`
1d
#50
0$
05
0]
0Y
0T
0O
0H
1%
16
1G
b00001100 '
b00001100 8
b00001100 b
b00001100 ^
b00001100 Z
b00001100 U
b00001100 P
b00001100 I
b00001100 D
b00101100 (
b00101100 9
b00101100 J
1)
1A
1e
0!
02
0C
0F
0L
0R
0W
0\
0`
0d
#55
1!
12
1C
1F
1L
1R
1W
1\
1`
1d
#60
0%
06
0G
0&
07
0X
b00011011 '
b00011011 8
b00011011 b
b00011011 ^
b00011011 Z
b00011011 U
b00011011 P
b00011011 I
b00011011 D
b01000101 (
b01000101 9
b01000101 J
0)
0A
0e
0!
02
0C
0F
0L
0R
0W
0\
0`
0d
#65
1!
12
1C
1F
1L
1R
1W
1\
1`
1d
#70
1"
13
1a
1S
1M
0#
04
0N
1$
15
1]
1Y
1T
1O
1H
1%
16
1G
1&
17
1X
b01101100 '
b01101100 8
b01101100 b
b01101100 ^
b01101100 Z
b01101100 U
b01101100 P
b01101100 I
b01101100 D
b01100111 (
b01100111 9
b01100111 J
0!
02
0C
0F
0L
0R
0W
0\
0`
0d
#75
1!
12
1C
1F
1L
1R
1W
1\
1`
1d
#80
0$
05
0]
0Y
0T
0O
0H
0%
06
0G
0&
07
0X
b01001010 '
b01001010 8
b01001010 b
b01001010 ^
b01001010 Z
b01001010 U
b01001010 P
b01001010 I
b01001010 D
b10100110 (
b10100110 9
b10100110 J
1)
1A
1e
0!
02
0C
0F
0L
0R
0W
0\
0`
0d
#85
1!
12
1C
1F
1L
1R
1W
1\
1`
1d
#90
1$
15
1]
1Y
1T
1O
1H
1%
16
1G
1&
17
1X
b10011101 '
b10011101 8
b10011101 b
b10011101 ^
b10011101 Z
b10011101 U
b10011101 P
b10011101 I
b10011101 D
b01111100 (
b01111100 9
b01111100 J
0)
0A
0e
0!
02
0C
0F
0L
0R
0W
0\
0`
0d
#95
1!
12
1C
1F
1L
1R
1W
1\
1`
1d
#100
1#
14
1N
0$
05
0]
0Y
0T
0O
0H
0%
06
0G
b11101011 '
b11101011 8
b11101011 b
b11101011 ^
b11101011 Z
b11101011 U
b11101011 P
b11101011 I
b11101011 D
b01011011 (
b01011011 9
b01011011 J
1)
1A
1e
0!
02
0C
0F
0L
0R
0W
0\
0`
0d
#105
1!
12
1C
1F
1L
1R
1W
1\
1`
1d
#110
0&
07
0X
b01001101 '
b01001101 8
b01001101 b
b01001101 ^
b01001101 Z
b01001101 U
b01001101 P
b01001101 I
b01001101 D
b01011100 (
b01011100 9
b01011100 J
0)
0A
0e
0!
02
0C
0F
0L
0R
0W
0\
0`
0d
#115
1!
12
1C
1F
1L
1R
1W
1\
1`
1d
#120
0"
03
0a
0S
0M
0#
04
0N
1$
15
1]
1Y
1T
1O
1H
b11011001 '
b11011001 8
b11011001 b
b11011001 ^
b11011001 Z
b11011001 U
b11011001 P
b11011001 I
b11011001 D
b10101001 (
b10101001 9
b10101001 J
0!
02
0C
0F
0L
0R
0W
0\
0`
0d
#125
1!
12
1C
1F
1L
1R
1W
1\
1`
1d
#130
1"
13
1a
1S
1M
1#
14
1N
0$
05
0]
0Y
0T
0O
0H
b10011110 '
b10011110 8
b10011110 b
b10011110 ^
b10011110 Z
b10011110 U
b10011110 P
b10011110 I
b10011110 D
b11001000 (
b11001000 9
b11001000 J
1)
1A
1e
0!
02
0C
0F
0L
0R
0W
0\
0`
0d
#135
1!
12
1C
1F
1L
1R
1W
1\
1`
1d
#140
0"
03
0a
0S
0M
0#
04
0N
1$
15
1]
1Y
1T
1O
1H
1%
16
1G
1&
17
1X
b00100110 '
b00100110 8
b00100110 b
b00100110 ^
b00100110 Z
b00100110 U
b00100110 P
b00100110 I
b00100110 D
b11110110 (
b11110110 9
b11110110 J
0)
0A
0e
0!
02
0C
0F
0L
0R
0W
0\
0`
0d
#145
1!
12
1C
1F
1L
1R
1W
1\
1`
1d
#150
1"
13
1a
1S
1M
1#
14
1N
0$
05
0]
0Y
0T
0O
0H
0%
06
0G
b01011011 '
b01011011 8
b01011011 b
b01011011 ^
b01011011 Z
b01011011 U
b01011011 P
b01011011 I
b01011011 D
b01000010 (
b01000010 9
b01000010 J
1)
1A
1e
0!
02
0C
0F
0L
0R
0W
0\
0`
0d
#155
1!
12
1C
1F
1L
1R
1W
1\
1`
1d
#160
b10010001 '
b10010001 8
b10010001 b
b10010001 ^
b10010001 Z
b10010001 U
b10010001 P
b10010001 I
b10010001 D
b00111000 (
b00111000 9
b00111000 J
0!
02
0C
0F
0L
0R
0W
0\
0`
0d
#165
1!
12
1C
1F
1L
1R
1W
1\
1`
1d
#170
0#
04
0N
1$
15
1]
1Y
1T
1O
1H
1%
16
1G
0&
07
0X
b01101101 '
b01101101 8
b01101101 b
b01101101 ^
b01101101 Z
b01101101 U
b01101101 P
b01101101 I
b01101101 D
b11000010 (
b11000010 9
b11000010 J
0!
02
0C
0F
0L
0R
0W
0\
0`
0d
#175
1!
12
1C
1F
1L
1R
1W
1\
1`
1d
#180
1#
14
1N
0%
06
0G
1&
17
1X
b01111100 '
b01111100 8
b01111100 b
b01111100 ^
b01111100 Z
b01111100 U
b01111100 P
b01111100 I
b01111100 D
b00101110 (
b00101110 9
b00101110 J
0!
02
0C
0F
0L
0R
0W
0\
0`
0d
#185
1!
12
1C
1F
1L
1R
1W
1\
1`
1d
#190
0#
04
0N
0$
05
0]
0Y
0T
0O
0H
0&
07
0X
b00011101 '
b00011101 8
b00011101 b
b00011101 ^
b00011101 Z
b00011101 U
b00011101 P
b00011101 I
b00011101 D
b11100011 (
b11100011 9
b11100011 J
0)
0A
0e
0!
02
0C
0F
0L
0R
0W
0\
0`
0d
#195
1!
12
1C
1F
1L
1R
1W
1\
1`
1d
#200
1#
14
1N
1&
17
1X
b00001010 '
b00001010 8
b00001010 b
b00001010 ^
b00001010 Z
b00001010 U
b00001010 P
b00001010 I
b00001010 D
b00010011 (
b00010011 9
b00010011 J
0!
02
0C
0F
0L
0R
0W
0\
0`
0d
#205
1!
12
1C
1F
1L
1R
1W
1\
1`
1d
#210
1$
15
1]
1Y
1T
1O
1H
1%
16
1G
0&
07
0X
b00111100 '
b00111100 8
b00111100 b
b00111100 ^
b00111100 Z
b00111100 U
b00111100 P
b00111100 I
b00111100 D
b00111010 (
b00111010 9
b00111010 J
0!
02
0C
0F
0L
0R
0W
0\
0`
0d
#215
1!
12
1C
1F
1L
1R
1W
1\
1`
1d
#220
0%
06
0G
b11100111 '
b11100111 8
b11100111 b
b11100111 ^
b11100111 Z
b11100111 U
b11100111 P
b11100111 I
b11100111 D
b10010111 (
b10010111 9
b10010111 J
1)
1A
1e
0!
02
0C
0F
0L
0R
0W
0\
0`
0d
#225
1!
12
1C
1F
1L
1R
1W
1\
1`
1d
#230
0"
03
0a
0S
0M
0#
04
0N
0$
05
0]
0Y
0T
0O
0H
b11100011 '
b11100011 8
b11100011 b
b11100011 ^
b11100011 Z
b11100011 U
b11100011 P
b11100011 I
b11100011 D
b00100000 (
b00100000 9
b00100000 J
0!
02
0C
0F
0L
0R
0W
0\
0`
0d
#235
1!
12
1C
1F
1L
1R
1W
1\
1`
1d
#240
1"
13
1a
1S
1M
1#
14
1N
1$
15
1]
1Y
1T
1O
1H
1%
16
1G
1&
17
1X
b10111111 '
b10111111 8
b10111111 b
b10111111 ^
b10111111 Z
b10111111 U
b10111111 P
b10111111 I
b10111111 D
b10010001 (
b10010001 9
b10010001 J
0!
02
0C
0F
0L
0R
0W
0\
0`
0d
#245
1!
12
1C
1F
1L
1R
1W
1\
1`
1d
#250
0"
03
0a
0S
0M
0%
06
0G
0&
07
0X
b01001100 '
b01001100 8
b01001100 b
b01001100 ^
b01001100 Z
b01001100 U
b01001100 P
b01001100 I
b01001100 D
b01110110 (
b01110110 9
b01110110 J
0)
0A
0e
0!
02
0C
0F
0L
0R
0W
0\
0`
0d
#255
1!
12
1C
1F
1L
1R
1W
1\
1`
1d
#260
1"
13
1a
1S
1M
0$
05
0]
0Y
0T
0O
0H
1%
16
1G
1&
17
1X
b00001100 (
b00001100 9
b00001100 J
1)
1A
1e
0!
02
0C
0F
0L
0R
0W
0\
0`
0d
#265
1!
12
1C
1F
1L
1R
1W
1\
1`
1d
#270
0%
06
0G
0&
07
0X
b11001000 '
b11001000 8
b11001000 b
b11001000 ^
b11001000 Z
b11001000 U
b11001000 P
b11001000 I
b11001000 D
b00011111 (
b00011111 9
b00011111 J
0!
02
0C
0F
0L
0R
0W
0\
0`
0d
#275
1!
12
1C
1F
1L
1R
1W
1\
1`
1d
#280
0#
04
0N
1&
17
1X
b00100011 '
b00100011 8
b00100011 b
b00100011 ^
b00100011 Z
b00100011 U
b00100011 P
b00100011 I
b00100011 D
b10011001 (
b10011001 9
b10011001 J
0)
0A
0e
0!
02
0C
0F
0L
0R
0W
0\
0`
0d
#285
1!
12
1C
1F
1L
1R
1W
1\
1`
1d
#290
1%
16
1G
0&
07
0X
b10001111 '
b10001111 8
b10001111 b
b10001111 ^
b10001111 Z
b10001111 U
b10001111 P
b10001111 I
b10001111 D
b11110110 (
b11110110 9
b11110110 J
1)
1A
1e
0!
02
0C
0F
0L
0R
0W
0\
0`
0d
#295
1!
12
1C
1F
1L
1R
1W
1\
1`
1d
#300
0"
03
0a
0S
0M
1$
15
1]
1Y
1T
1O
1H
0%
06
0G
b11110111 '
b11110111 8
b11110111 b
b11110111 ^
b11110111 Z
b11110111 U
b11110111 P
b11110111 I
b11110111 D
b00001110 (
b00001110 9
b00001110 J
0)
0A
0e
0!
02
0C
0F
0L
0R
0W
0\
0`
0d
#305
1!
12
1C
1F
1L
1R
1W
1\
1`
1d
#310
1"
13
1a
1S
1M
1%
16
1G
1&
17
1X
b01101101 '
b01101101 8
b01101101 b
b01101101 ^
b01101101 Z
b01101101 U
b01101101 P
b01101101 I
b01101101 D
b00000110 (
b00000110 9
b00000110 J
0!
02
0C
0F
0L
0R
0W
0\
0`
0d
#315
1!
12
1C
1F
1L
1R
1W
1\
1`
1d
#320
1#
14
1N
0$
05
0]
0Y
0T
0O
0H
0%
06
0G
0&
07
0X
b00011010 '
b00011010 8
b00011010 b
b00011010 ^
b00011010 Z
b00011010 U
b00011010 P
b00011010 I
b00011010 D
b10001111 (
b10001111 9
b10001111 J
1)
1A
1e
0!
02
0C
0F
0L
0R
0W
0\
0`
0d
#325
1!
12
1C
1F
1L
1R
1W
1\
1`
1d
#330
0#
04
0N
1%
16
1G
1&
17
1X
b00101111 '
b00101111 8
b00101111 b
b00101111 ^
b00101111 Z
b00101111 U
b00101111 P
b00101111 I
b00101111 D
b00100001 (
b00100001 9
b00100001 J
0)
0A
0e
0!
02
0C
0F
0L
0R
0W
0\
0`
0d
#335
1!
12
1C
1F
1L
1R
1W
1\
1`
1d
#340
0"
03
0a
0S
0M
b00001111 '
b00001111 8
b00001111 b
b00001111 ^
b00001111 Z
b00001111 U
b00001111 P
b00001111 I
b00001111 D
b01110100 (
b01110100 9
b01110100 J
0!
02
0C
0F
0L
0R
0W
0\
0`
0d
#345
1!
12
1C
1F
1L
1R
1W
1\
1`
1d
#350
b01000111 '
b01000111 8
b01000111 b
b01000111 ^
b01000111 Z
b01000111 U
b01000111 P
b01000111 I
b01000111 D
b00111101 (
b00111101 9
b00111101 J
0!
02
0C
0F
0L
0R
0W
0\
0`
0d
#355
1!
12
1C
1F
1L
1R
1W
1\
1`
1d
#360
0&
07
0X
b10011100 '
b10011100 8
b10011100 b
b10011100 ^
b10011100 Z
b10011100 U
b10011100 P
b10011100 I
b10011100 D
b00111110 (
b00111110 9
b00111110 J
0!
02
0C
0F
0L
0R
0W
0\
0`
0d
#365
1!
12
1C
1F
1L
1R
1W
1\
1`
1d
#370
1#
14
1N
0%
06
0G
b10010100 '
b10010100 8
b10010100 b
b10010100 ^
b10010100 Z
b10010100 U
b10010100 P
b10010100 I
b10010100 D
b10100101 (
b10100101 9
b10100101 J
1)
1A
1e
0!
02
0C
0F
0L
0R
0W
0\
0`
0d
#375
1!
12
1C
1F
1L
1R
1W
1\
1`
1d
#380
1"
13
1a
1S
1M
0#
04
0N
1$
15
1]
1Y
1T
1O
1H
1%
16
1G
b11100010 '
b11100010 8
b11100010 b
b11100010 ^
b11100010 Z
b11100010 U
b11100010 P
b11100010 I
b11100010 D
b01000001 (
b01000001 9
b01000001 J
0!
02
0C
0F
0L
0R
0W
0\
0`
0d
#385
1!
12
1C
1F
1L
1R
1W
1\
1`
1d
#390
0"
03
0a
0S
0M
0$
05
0]
0Y
0T
0O
0H
b00110101 '
b00110101 8
b00110101 b
b00110101 ^
b00110101 Z
b00110101 U
b00110101 P
b00110101 I
b00110101 D
b00011101 (
b00011101 9
b00011101 J
0)
0A
0e
0!
02
0C
0F
0L
0R
0W
0\
0`
0d
#395
1!
12
1C
1F
1L
1R
1W
1\
1`
1d
#400
1&
17
1X
b11000011 '
b11000011 8
b11000011 b
b11000011 ^
b11000011 Z
b11000011 U
b11000011 P
b11000011 I
b11000011 D
b00111101 (
b00111101 9
b00111101 J
1)
1A
1e
0!
02
0C
0F
0L
0R
0W
0\
0`
0d
#405
1!
12
1C
1F
1L
1R
1W
1\
1`
1d
#410
1"
13
1a
1S
1M
1$
15
1]
1Y
1T
1O
1H
b10111110 '
b10111110 8
b10111110 b
b10111110 ^
b10111110 Z
b10111110 U
b10111110 P
b10111110 I
b10111110 D
b10001100 (
b10001100 9
b10001100 J
0!
02
0C
0F
0L
0R
0W
0\
0`
0d
#415
1!
12
1C
1F
1L
1R
1W
1\
1`
1d
#420
0"
03
0a
0S
0M
b00111000 '
b00111000 8
b00111000 b
b00111000 ^
b00111000 Z
b00111000 U
b00111000 P
b00111000 I
b00111000 D
b11001110 (
b11001110 9
b11001110 J
0!
02
0C
0F
0L
0R
0W
0\
0`
0d
#425
1!
12
1C
1F
1L
1R
1W
1\
1`
1d
#430
1"
13
1a
1S
1M
1#
14
1N
0$
05
0]
0Y
0T
0O
0H
b01100101 '
b01100101 8
b01100101 b
b01100101 ^
b01100101 Z
b01100101 U
b01100101 P
b01100101 I
b01100101 D
b00001100 (
b00001100 9
b00001100 J
0!
02
0C
0F
0L
0R
0W
0\
0`
0d
#435
1!
12
1C
1F
1L
1R
1W
1\
1`
1d
#440
0"
03
0a
0S
0M
0#
04
0N
0%
06
0G
b11110010 '
b11110010 8
b11110010 b
b11110010 ^
b11110010 Z
b11110010 U
b11110010 P
b11110010 I
b11110010 D
b10000000 (
b10000000 9
b10000000 J
0!
02
0C
0F
0L
0R
0W
0\
0`
0d
#445
1!
12
1C
1F
1L
1R
1W
1\
1`
1d
#450
1"
13
1a
1S
1M
1%
16
1G
0&
07
0X
b00010000 '
b00010000 8
b00010000 b
b00010000 ^
b00010000 Z
b00010000 U
b00010000 P
b00010000 I
b00010000 D
b01100110 (
b01100110 9
b01100110 J
0)
0A
0e
0!
02
0C
0F
0L
0R
0W
0\
0`
0d
#455
1!
12
1C
1F
1L
1R
1W
1\
1`
1d
#460
0"
03
0a
0S
0M
1#
14
1N
0%
06
0G
1&
17
1X
b01010110 '
b01010110 8
b01010110 b
b01010110 ^
b01010110 Z
b01010110 U
b01010110 P
b01010110 I
b01010110 D
b10110011 (
b10110011 9
b10110011 J
0!
02
0C
0F
0L
0R
0W
0\
0`
0d
#465
1!
12
1C
1F
1L
1R
1W
1\
1`
1d
#470
0#
04
0N
1$
15
1]
1Y
1T
1O
1H
1%
16
1G
b01000110 '
b01000110 8
b01000110 b
b01000110 ^
b01000110 Z
b01000110 U
b01000110 P
b01000110 I
b01000110 D
b01110100 (
b01110100 9
b01110100 J
0!
02
0C
0F
0L
0R
0W
0\
0`
0d
#475
1!
12
1C
1F
1L
1R
1W
1\
1`
1d
#480
0$
05
0]
0Y
0T
0O
0H
0&
07
0X
b00100100 '
b00100100 8
b00100100 b
b00100100 ^
b00100100 Z
b00100100 U
b00100100 P
b00100100 I
b00100100 D
b00001111 (
b00001111 9
b00001111 J
0!
02
0C
0F
0L
0R
0W
0\
0`
0d
#485
1!
12
1C
1F
1L
1R
1W
1\
1`
1d
#490
1#
14
1N
0%
06
0G
b10100111 '
b10100111 8
b10100111 b
b10100111 ^
b10100111 Z
b10100111 U
b10100111 P
b10100111 I
b10100111 D
b10111111 (
b10111111 9
b10111111 J
1)
1A
1e
0!
02
0C
0F
0L
0R
0W
0\
0`
0d
#495
1!
12
1C
1F
1L
1R
1W
1\
1`
1d
#500
b00010010 '
b00010010 8
b00010010 b
b00010010 ^
b00010010 Z
b00010010 U
b00010010 P
b00010010 I
b00010010 D
b00111010 (
b00111010 9
b00111010 J
0!
02
0C
0F
0L
0R
0W
0\
0`
0d
#505
1!
12
1C
1F
1L
1R
1W
1\
1`
1d
#510
1"
13
1a
1S
1M
1%
16
1G
1&
17
1X
b01101101 '
b01101101 8
b01101101 b
b01101101 ^
b01101101 Z
b01101101 U
b01101101 P
b01101101 I
b01101101 D
b10111110 (
b10111110 9
b10111110 J
0)
0A
0e
0!
02
0C
0F
0L
0R
0W
0\
0`
0d
#515
1!
12
1C
1F
1L
1R
1W
1\
1`
1d
#520
b11010001 '
b11010001 8
b11010001 b
b11010001 ^
b11010001 Z
b11010001 U
b11010001 P
b11010001 I
b11010001 D
b01110000 (
b01110000 9
b01110000 J
0!
02
0C
0F
0L
0R
0W
0\
0`
0d
#525
1!
12
1C
1F
1L
1R
1W
1\
1`
1d
#530
0#
04
0N
0&
07
0X
b10110100 '
b10110100 8
b10110100 b
b10110100 ^
b10110100 Z
b10110100 U
b10110100 P
b10110100 I
b10110100 D
b10010101 (
b10010101 9
b10010101 J
1)
1A
1e
0!
02
0C
0F
0L
0R
0W
0\
0`
0d
#535
1!
12
1C
1F
1L
1R
1W
1\
1`
1d
#540
0"
03
0a
0S
0M
1#
14
1N
1$
15
1]
1Y
1T
1O
1H
0%
06
0G
b00011010 '
b00011010 8
b00011010 b
b00011010 ^
b00011010 Z
b00011010 U
b00011010 P
b00011010 I
b00011010 D
b10111000 (
b10111000 9
b10111000 J
0!
02
0C
0F
0L
0R
0W
0\
0`
0d
#545
1!
12
1C
1F
1L
1R
1W
1\
1`
1d
#550
1"
13
1a
1S
1M
0#
04
0N
0$
05
0]
0Y
0T
0O
0H
1%
16
1G
b10011101 '
b10011101 8
b10011101 b
b10011101 ^
b10011101 Z
b10011101 U
b10011101 P
b10011101 I
b10011101 D
b00101010 (
b00101010 9
b00101010 J
0!
02
0C
0F
0L
0R
0W
0\
0`
0d
#555
1!
12
1C
1F
1L
1R
1W
1\
1`
1d
#560
1#
14
1N
b11001100 '
b11001100 8
b11001100 b
b11001100 ^
b11001100 Z
b11001100 U
b11001100 P
b11001100 I
b11001100 D
b00100011 (
b00100011 9
b00100011 J
0!
02
0C
0F
0L
0R
0W
0\
0`
0d
#565
1!
12
1C
1F
1L
1R
1W
1\
1`
1d
#570
0#
04
0N
b11010001 '
b11010001 8
b11010001 b
b11010001 ^
b11010001 Z
b11010001 U
b11010001 P
b11010001 I
b11010001 D
b01001010 (
b01001010 9
b01001010 J
0)
0A
0e
0!
02
0C
0F
0L
0R
0W
0\
0`
0d
#575
1!
12
1C
1F
1L
1R
1W
1\
1`
1d
#580
0"
03
0a
0S
0M
1$
15
1]
1Y
1T
1O
1H
1&
17
1X
b11010100 '
b11010100 8
b11010100 b
b11010100 ^
b11010100 Z
b11010100 U
b11010100 P
b11010100 I
b11010100 D
b01000000 (
b01000000 9
b01000000 J
1)
1A
1e
0!
02
0C
0F
0L
0R
0W
0\
0`
0d
#585
1!
12
1C
1F
1L
1R
1W
1\
1`
1d
#590
1"
13
1a
1S
1M
1#
14
1N
0$
05
0]
0Y
0T
0O
0H
b10100011 '
b10100011 8
b10100011 b
b10100011 ^
b10100011 Z
b10100011 U
b10100011 P
b10100011 I
b10100011 D
b01111101 (
b01111101 9
b01111101 J
0!
02
0C
0F
0L
0R
0W
0\
0`
0d
#595
1!
12
1C
1F
1L
1R
1W
1\
1`
1d
#600
0#
04
0N
0%
06
0G
0&
07
0X
b10111011 '
b10111011 8
b10111011 b
b10111011 ^
b10111011 Z
b10111011 U
b10111011 P
b10111011 I
b10111011 D
b01110010 (
b01110010 9
b01110010 J
0!
02
0C
0F
0L
0R
0W
0\
0`
0d
#605
1!
12
1C
1F
1L
1R
1W
1\
1`
1d
#610
0"
03
0a
0S
0M
1$
15
1]
1Y
1T
1O
1H
1%
16
1G
1&
17
1X
b10101000 '
b10101000 8
b10101000 b
b10101000 ^
b10101000 Z
b10101000 U
b10101000 P
b10101000 I
b10101000 D
b01101001 (
b01101001 9
b01101001 J
0!
02
0C
0F
0L
0R
0W
0\
0`
0d
#615
1!
12
1C
1F
1L
1R
1W
1\
1`
1d
